mkdocs_minify_html_plugin-0.3.8.dist-info/METADATA
mkdocs_minify_html_plugin-0.3.8.dist-info/WHEEL
mkdocs_minify_html_plugin-0.3.8.dist-info/entry_points.txt
mkdocs_minify_html_plugin-0.3.8.dist-info/licenses/LICENSE
mkdocs_minify_html_plugin/__init__.py
mkdocs_minify_html_plugin/_minify_html.cpython-312-aarch64-linux-gnu.so
mkdocs_minify_html_plugin/_minify_html.pyi
mkdocs_minify_html_plugin/plugin.py
mkdocs_minify_html_plugin/py.typed
mkdocs_minify_html_plugin-0.3.8.dist-info/RECORD
