Metadata-Version: 2.4
Name: mkdocs-minify-html-plugin
Version: 0.3.8
Classifier: Framework :: MkDocs
Classifier: Natural Language :: English
Classifier: Operating System :: MacOS
Classifier: Operating System :: Microsoft :: Windows
Classifier: Operating System :: POSIX :: Linux
Classifier: Programming Language :: Python
Classifier: Programming Language :: Python :: 3 :: Only
Classifier: Programming Language :: Python :: 3.9
Classifier: Programming Language :: Python :: 3.10
Classifier: Programming Language :: Python :: 3.11
Classifier: Programming Language :: Python :: 3.12
Classifier: Programming Language :: Python :: 3.13
Classifier: Programming Language :: Python :: 3.14
Classifier: Programming Language :: Python :: Implementation :: CPython
Classifier: Programming Language :: Python :: Implementation :: PyPy
Classifier: Programming Language :: Rust
Classifier: Typing :: Typed
Requires-Dist: mkdocs>=1.4
Requires-Dist: typing-extensions>=4.4 ; python_full_version < '3.12'
License-File: LICENSE
Summary: MkDocs plugin for minification using minify-html, an extremely fast and smart HTML + JS + CSS minifier
Author-email: monosans <hsyqixco@protonmail.com>
Requires-Python: >=3.9
Project-URL: repository, https://github.com/monosans/mkdocs-minify-html-plugin
